gravely/__init__.py
gravely/__main__.py
gravely/body.cpython-35m-x86_64-linux-gnu.so
gravely/body.pxd
gravely/body.pyx
gravely/configuration.py
gravely/diagnostics.py
gravely/main.py
gravely/simulation.py
gravely/solver.cpython-35m-x86_64-linux-gnu.so
gravely/solver.pyx
gravely/units.py
gravely/tests/__init__.py
gravely/tests/run.py
gravely/tests/express/__init__.py
gravely/tests/express/test_argparse.py
gravely/tests/express/test_body.py
gravely/tests/express/test_configuration.py
gravely/tests/integration/__init__.py
gravely/tests/integration/test_crude.py
gravely/utils/__init__.py
gravely/utils/progress.py
gravely-0.0.2.dev17.dist-info/DESCRIPTION.rst
gravely-0.0.2.dev17.dist-info/METADATA
gravely-0.0.2.dev17.dist-info/RECORD
gravely-0.0.2.dev17.dist-info/WHEEL
gravely-0.0.2.dev17.dist-info/entry_points.txt
gravely-0.0.2.dev17.dist-info/metadata.json
gravely-0.0.2.dev17.dist-info/pbr.json
gravely-0.0.2.dev17.dist-info/top_level.txt
