Metadata-Version: 2.0
Name: gravely
Version: 0.0.2.dev17
Summary: A gravity simulator written to taste modern Python packaging practices
Home-page: https://lcode.info/mainline/gravely
Author: LCODE Team
Author-email: team@lcode.info
License: 'MIT'
Keywords: cython
Requires-Dist: h5py (>=2.2)
Requires-Dist: numpy (>=1.8.2)
Requires-Dist: progressbar2 (>=3.10)
Provides-Extra: diagnostics
Requires-Dist: matplotlib (>=1.4); extra == 'diagnostics'
Provides-Extra: test
Requires-Dist: nose (>=1.0); extra == 'test'
